CADETMatch/__init__.py
CADETMatch/__main__.py
CADETMatch/cache.py
CADETMatch/calc_coeff.py
CADETMatch/clean_examples.py
CADETMatch/create_example_config.py
CADETMatch/create_example_sims.py
CADETMatch/create_examples.py
CADETMatch/de.py
CADETMatch/de_snooker.py
CADETMatch/evo.py
CADETMatch/fitness.py
CADETMatch/gen_prior.py
CADETMatch/generate_autocorr_graphs.py
CADETMatch/generate_corner_graphs.py
CADETMatch/generate_examples.py
CADETMatch/generate_graphs.py
CADETMatch/generate_mixing_graphs.py
CADETMatch/gradFD.py
CADETMatch/graph_kde.py
CADETMatch/jacobian.py
CADETMatch/jupyter.py
CADETMatch/kde_generator.py
CADETMatch/kde_util.py
CADETMatch/loggerwriter.py
CADETMatch/match.py
CADETMatch/mcmc_plot_tube.py
CADETMatch/mle.py
CADETMatch/pareto.py
CADETMatch/plugins.py
CADETMatch/pop.py
CADETMatch/progress.py
CADETMatch/pymoo_config.py
CADETMatch/results_examples.py
CADETMatch/run_examples.py
CADETMatch/score.py
CADETMatch/score_calc.py
CADETMatch/smoothing.py
CADETMatch/stretch.py
CADETMatch/sub.py
CADETMatch/synthetic_error.py
CADETMatch/util.py
CADETMatch/version.py
CADETMatch/abstract/__init__.py
CADETMatch/abstract/transform.py
CADETMatch/scores/__init__.py
CADETMatch/scores/absoluteHeight.py
CADETMatch/scores/absoluteTime.py
CADETMatch/scores/ceiling.py
CADETMatch/scores/curve.py
CADETMatch/scores/dextranSSE.py
CADETMatch/scores/dextranShape.py
CADETMatch/scores/fractionationSSE.py
CADETMatch/scores/fractionationSlide.py
CADETMatch/scores/shape.py
CADETMatch/scores/shapeBack.py
CADETMatch/scores/shapeDecay.py
CADETMatch/scores/shapeDecayNoDer.py
CADETMatch/scores/shapeDecaySimple.py
CADETMatch/scores/shapeFront.py
CADETMatch/scores/shapeNoDer.py
CADETMatch/scores/shapeOnly.py
CADETMatch/scores/shapeSimple.py
CADETMatch/scores/similarity.py
CADETMatch/scores/similarityDecay.py
CADETMatch/scores/sse.py
CADETMatch/search/__init__.py
CADETMatch/search/altScore.py
CADETMatch/search/gradient.py
CADETMatch/search/graphSpace.py
CADETMatch/search/mcmc.py
CADETMatch-0.8.16.dist-info/METADATA
CADETMatch-0.8.16.dist-info/WHEEL
CADETMatch-0.8.16.dist-info/top_level.txt
CADETMatch-0.8.16.dist-info/RECORD
